setup.py
liza_distributions_moscow/Binomialdistribution.py
liza_distributions_moscow/Gaussiandistribution.py
liza_distributions_moscow/Generaldistribution.py
liza_distributions_moscow/__init__.py
liza_distributions_moscow.egg-info/PKG-INFO
liza_distributions_moscow.egg-info/SOURCES.txt
liza_distributions_moscow.egg-info/dependency_links.txt
liza_distributions_moscow.egg-info/not-zip-safe
liza_distributions_moscow.egg-info/top_level.txt